{
    "name": "Gastropolis Awards",
    "assetPath": "minecraft",
    "categories": [
        {
            "title": "Best Place to Get Faded at",
            "options": [
                {
                    "name": "Circle K Tower Business Room",
                    "creator": "Pat",
                    "asset": "best-place-faded/circle-k-tower-stocks.jpeg"
                },
                {
                    "name": "IGG Towers Penthouse Balcony",
                    "creator": "Shan",
                    "asset": "best-place-faded/igg-tower-top.jpeg"
                },
                {
                    "name": "IGG Gaff Balcony",
                    "creator": "Liam, Dima, Shan, Pat, Kingers",
                    "asset": "best-place-faded/igg-gaff-balcony.jpeg"
                }
            ]
        },
        {
            "title": "Best Armor Trim",
            "subtitle": "Drag a trim to rotate it",
            "options": [
                {
                    "name": "Silence",
                    "creator": "Liam",
                    "asset": "best-trim/liam.trim.json"
                },
                {
                    "name": "Sentry, Snout, Sentry, Dune",
                    "creator": "Kingers",
                    "asset": "best-trim/kingers.trim.json"
                },
                {
                    "name": "Flow",
                    "creator": "Pat",
                    "asset": "best-trim/pat.trim.json"
                },
                {
                    "name": "Coast, Snout, Host, Bolt",
                    "creator": "Shan",
                    "asset": "best-trim/shan.trim.json"
                },
                {
                    "name": "Flow",
                    "creator": "Dima",
                    "asset": "best-trim/dima.trim.json"
                }
            ]
        },
        {
            "title": "Best Concept",
            "options": [
                {
                    "name": "Shan York Arch",
                    "creator": "Shan",
                    "asset": "best-concept/shan-york-arch.jpeg"
                },
                {
                    "name": "PistolWhip Statue",
                    "creator": "Kingers",
                    "asset": "best-concept/wistol-statue.jpeg"
                },
                {
                    "name": "Backrooms Tower",
                    "creator": "Pat, Shan",
                    "asset": "best-concept/backrooms-tower.jpeg"
                },
                {
                    "name": "Blocks Statue",
                    "creator": "Pat",
                    "asset": "placeholder.jpeg"
                }
            ]
        },
         {
            "title": "Best Destroyed Build (RIP)",
            "options": [
                {
                    "name": "C House",
                    "creator": "Dima",
                    "asset": "best-destroyed-build/c-house.jpeg"
                },
                {
                    "name": "Epstein Temple",
                    "creator": "Pat, Shan",
                    "asset": "best-destroyed-build/epstein-temple.jpeg"
                },
                {
                    "name": "Liam Gaff (Early Gas)",
                    "creator": "Liam",
                    "asset": "best-destroyed-build/liam-gaff-early.jpeg"
                },
                {
                    "name": "Liam Gaff (Late Gas)",
                    "creator": "Liam",
                    "asset": "best-destroyed-build/liam-gaff-late.jpeg"
                }
            ]
        }
    ]
}